sumeh/__init__.py
sumeh/cli/__init__.py
sumeh/core/__init__.py
sumeh/core/config.py
sumeh/core/io.py
sumeh/core/report.py
sumeh/core/rules/__init__.py
sumeh/core/rules/manifest.json
sumeh/core/rules/regristry.py
sumeh/core/rules/rule_model.py
sumeh/core/utils.py
sumeh/dash/__init__.py
sumeh/dash/app.py
sumeh/dash/index.html
sumeh/engines/__init__.py
sumeh/engines/bigquery_engine.py
sumeh/engines/dask_engine.py
sumeh/engines/duckdb_engine.py
sumeh/engines/pandas_engine.py
sumeh/engines/polars_engine.py
sumeh/engines/pyspark_engine.py
sumeh/generators/__init__.py
sumeh-1.3.0.dist-info/METADATA
sumeh-1.3.0.dist-info/WHEEL
sumeh-1.3.0.dist-info/entry_points.txt
sumeh-1.3.0.dist-info/licenses/LICENSE
sumeh-1.3.0.dist-info/RECORD
