Metadata-Version: 2.4
Name: sumeh
Version: 1.3.0
Summary: Unified Data Quality Validation Framework
License: Apache-2.0
License-File: LICENSE
Keywords: data-quality,validation,dq,etl,cli
Author: Demetrius Albuquerque
Author-email: demetrius.albuquerque@yahoo.com.br
Requires-Python: >=3.10,<4.0
Classifier: Development Status :: 4 - Beta
Classifier: Environment :: Console
Classifier: Intended Audience :: Developers
Classifier: Intended Audience :: Science/Research
Classifier: License :: OSI Approved :: Apache Software License
Classifier: Operating System :: OS Independent
Classifier: Programming Language :: Python :: 3
Classifier: Programming Language :: Python :: 3.10
Classifier: Programming Language :: Python :: 3.11
Classifier: Programming Language :: Python :: 3.12
Classifier: Programming Language :: Python :: 3.13
Classifier: Programming Language :: Python :: 3.14
Classifier: Topic :: Software Development :: Libraries
Classifier: Topic :: Software Development :: Quality Assurance
Classifier: Topic :: Utilities
Classifier: Typing :: Typed
Provides-Extra: aws
Provides-Extra: bigquery
Provides-Extra: dashboard
Provides-Extra: dask
Provides-Extra: dev
Provides-Extra: mysql
Provides-Extra: postgresql
Provides-Extra: pyspark
Requires-Dist: boto3 (>=1.38.17,<2.0.0) ; extra == "aws"
Requires-Dist: cuallee (>=0.15.2,<0.16.0)
Requires-Dist: dask[complete] (>=2025.10.0,<2026.0.0) ; extra == "dask"
Requires-Dist: google-cloud-bigquery (==3.32.0) ; extra == "bigquery"
Requires-Dist: mysql-connector-python (>=9.3.0,<10.0.0) ; extra == "mysql"
Requires-Dist: pandas (>=2.2.0,<3.0.0) ; extra == "aws" or extra == "mysql" or extra == "postgresql" or extra == "bigquery"
Requires-Dist: psycopg2-binary (>=2.9.1,<3.0.0) ; extra == "postgresql"
Requires-Dist: pyspark (>=3.5.0,<4.0.0) ; extra == "pyspark"
Requires-Dist: python-dateutil (>=2.8.0,<3.0.0)
Requires-Dist: rich (>=14.2.0,<15.0.0)
Requires-Dist: sqlglot (>=27.24.2,<28.0.0)
Requires-Dist: typer (>=0.19.0,<0.20.0)
Project-URL: Bug Tracker, https://github.com/maltzsama/sumeh/issues
Project-URL: Documentation, https://maltzsama.github.io/sumeh
Project-URL: Homepage, https://github.com/maltzsama/sumeh
Project-URL: Repository, https://github.com/maltzsama/sumeh
